{
	"publisher_id": 0,
	"publisher_package_id": 3289,
	"title": "ex2D",
	"description": "<p>\nex2D is a highly integrated 2D-sprite-related development extension for Unity. It aims at providing high performance 2D sprite/UI solution inside Unity, with a specific focus on creating tons of cutting-edge sprite animations and other content in complicated Unity scenes, while still maintaining great performance on mobile devices.\n</p>\n<br></br>\n<p><strong>Links:</strong></p>\n> <a href=\"http://www.ex-dev.com/ex2d\">ex2D Website</a>\n |  <a href=\"http://www.ex-dev.com/ex2d/wiki\">Online Documentation</a>\n |  <a href=\"http://www.ex-dev.com/ex2d/wiki/doku.php?id=misc:change_log\">Change List</a>\n |  <a href=\"http://forum.unity3d.com/threads/101811-ex2D-the-best-2D-sprite-solution-for-Unity-RELEASED\">Forum Thread</a>\n</p>\n\n<p><strong>Downloads:</strong></p>\n<p>\n> <a href=\"http://www.ex-dev.com/downloads/ex2d_doc.zip\">Offline Documentation</a>\n |  <a href=\"http://www.ex-dev.com/downloads/ex2d_script_ref.zip\">Offline Script Reference</a>\n</p>\n\n<p><strong>Important:</strong></p>\n<p>\n> <a href=\"http://www.ex-dev.com/ex2d/wiki/doku.php?id=manual:install#upgrade_to_v122\">Upgrade from ex2D v1.2.1 to v1.2.2</a></p>\n</p>",
	"changes": "  * New Features\n    * Add Rebuild Prefabs in Edit/ex2D/Command menu. (Help user update prefabs in project when atlas changes).\n    * Add New Layer System, exLayerMng, exLayer.\n\n  * Changes\n    * Disable atlas texture Read/Write settings after atlas texture built\n    * Use exSpriteMng update sprites instead of updating all sprites in each LateUpdate function (it also longer the battery life and the device will not get too hot)\n    * Fix sprite animation play hidden sprite will show last frame at first.\n    * Change exSpriteAnimation.Play() to exSpriteAnimation.PlayDefault() so it will not conflict with Play(string) when setup animation event in animation view.\n    * Disable exSpriteAnimation when animation paused or stopped. \n    * Disable exSpriteAnimation when the game started but no default animation played.\n    * Remove exPlane.plane, instead we assume user working in XY coordinate space\n    * Remove exLayer2D, use new layer system exLayerMng instead of it.\n\n  * Bug Fix\n    * Fix sprite animation trigger event that play current animation again has no effect.\n    * Fix SoftClip not update immediately when sprite postion changed.\n    * Fix sprite font line height calculate wrong when scaled\n    * Fix animation helper keep reporting error when upgrade ex2D.\n    * Fix spriteMng commit error when guiBorder is null\n    * Fix exScreenPosition, exViewportPosition not work with Perspective camera",
	"version_name": "1.2.2 RC3",
	"category": 102,
	"price": "35",
	"recommended_features": [],
	"required_features": []
}
